tft_forecasting/__init__.py
tft_forecasting/model/__init__.py
tft_forecasting/model/components/__init__.py
tft_forecasting/model/components/gate_add_norm.py
tft_forecasting/model/components/glu.py
tft_forecasting/model/components/grn.py
tft_forecasting/model/components/lstm.py
tft_forecasting/model/components/variable_selection.py
tft_forecasting/model/functions.py
tft_forecasting/model/tft.py
tft_forecasting-0.1.0.dist-info/LICENSE
tft_forecasting-0.1.0.dist-info/METADATA
tft_forecasting-0.1.0.dist-info/WHEEL
tft_forecasting-0.1.0.dist-info/RECORD
